pyfastscreencap/__init__.py
pyfastscreencap/pyfastscreencap.py
pyfastscreencap/settingsfiller.py
pyfastscreencap/binaries/ffmpeg.exe
pyfastscreencap-1.0.1.dist-info/METADATA
pyfastscreencap-1.0.1.dist-info/WHEEL
pyfastscreencap-1.0.1.dist-info/licenses/LICENSE
pyfastscreencap-1.0.1.dist-info/RECORD
