Metadata-Version: 2.3
Name: pyfastscreencap
Version: 1.0.1
Summary: A lightning fast Windows screen recorder that can record up to your monitors refresh rate by leveraging DXCam and ffmpeg
Project-URL: Homepage, https://github.com/tezzary/pyfastscreencap
Project-URL: Issues, https://github.com/tezzary/pyfastscreencap/issues
Author-email: tezzary <tezzary1@gmail.com>
License-File: LICENSE
Classifier: License :: OSI Approved :: MIT License
Classifier: Operating System :: OS Independent
Classifier: Programming Language :: Python :: 3
Requires-Python: >=3.8
Requires-Dist: dxcam
Requires-Dist: numpy
